Metadata-Version: 2.1
Name: covid-py
Version: 0.1.8
Summary: Analysis of Corona Dataset
Home-page: UNKNOWN
Author: Sirisha Cherala
Author-email: sirishacherala@gmail.com
License: MIT
Keywords: Coronavirus,COVID
Platform: UNKNOWN
